sip_core/__about__.py
sip_core/__init__.py
sip_core-0.0.1.dist-info/METADATA
sip_core-0.0.1.dist-info/WHEEL
sip_core-0.0.1.dist-info/licenses/LICENSE
sip_core-0.0.1.dist-info/RECORD
