Metadata-Version: 2.4
Name: sip-core
Version: 0.0.1
Summary: Core elements of the SIP protocol (RFC 3261)
Project-URL: Documentation, https://github.com/rhjdjong/sip-core#readme
Project-URL: Issues, https://github.com/rhjdjong/sip-core/issues
Project-URL: Source, https://github.com/rhjdjong/sip-core
Author-email: Ruud de Jong <rhjdjong@users.noreply.github.com>
License-Expression: MIT
License-File: LICENSE
Keywords: RFC3261,SIP
Classifier: Development Status :: 4 - Beta
Classifier: Programming Language :: Python
Classifier: Programming Language :: Python :: 3.8
Classifier: Programming Language :: Python :: 3.9
Classifier: Programming Language :: Python :: 3.10
Classifier: Programming Language :: Python :: 3.11
Classifier: Programming Language :: Python :: 3.12
Classifier: Programming Language :: Python :: Implementation :: CPython
Classifier: Programming Language :: Python :: Implementation :: PyPy
Requires-Python: >=3.8
